synapse_pb/__init__.py
synapse_pb/actuators_pb2.py
synapse_pb/altimeter_pb2.py
synapse_pb/battery_state_pb2.py
synapse_pb/bezier_trajectory_pb2.py
synapse_pb/clock_offset_pb2.py
synapse_pb/covariance3_pb2.py
synapse_pb/covariance6_pb2.py
synapse_pb/duration_pb2.py
synapse_pb/frame_pb2.py
synapse_pb/imu_pb2.py
synapse_pb/imu_q31_array_pb2.py
synapse_pb/input_pb2.py
synapse_pb/led_array_pb2.py
synapse_pb/magnetic_field_pb2.py
synapse_pb/nav_sat_fix_pb2.py
synapse_pb/odometry_pb2.py
synapse_pb/pose_pb2.py
synapse_pb/pwm_pb2.py
synapse_pb/quaternion_pb2.py
synapse_pb/safety_pb2.py
synapse_pb/sim_clock_pb2.py
synapse_pb/status_pb2.py
synapse_pb/timestamp_pb2.py
synapse_pb/twist_pb2.py
synapse_pb/vector3_pb2.py
synapse_pb/wheel_odometry_pb2.py
synapse_pb-0.2.11.dist-info/METADATA
synapse_pb-0.2.11.dist-info/WHEEL
synapse_pb-0.2.11.dist-info/RECORD
